optionvisualizer_wrapper/__init__.py
optionvisualizer_wrapper/config.py
optionvisualizer_wrapper/projection.py
optionvisualizer_wrapper/surface.py
optionvisualizer_wrapper/utils.py
optionvisualizer_wrapper/wrapper.py
optionvisualizer_wrapper-10.0.2.dist-info/METADATA
optionvisualizer_wrapper-10.0.2.dist-info/WHEEL
optionvisualizer_wrapper-10.0.2.dist-info/RECORD
